CHANGES.md
LICENSE.md
MANIFEST.in
README.md
VERSION
pyproject.toml
requirements-docs.txt
requirements-tests.txt
requirements.txt
setup.cfg
setup.py
skeletons.txt
bin/radical-synapse-atom.py
bin/radical-synapse-emulate
bin/radical-synapse-execute
bin/radical-synapse-fixdocs
bin/radical-synapse-iotrace.sh
bin/radical-synapse-mandelbrot-dummy.py
bin/radical-synapse-mandelbrot-emulate.py
bin/radical-synapse-mandelbrot-master.py
bin/radical-synapse-mandelbrot-profile.py
bin/radical-synapse-mandelbrot-worker.py
bin/radical-synapse-profile
bin/radical-synapse-rename
bin/radical-synapse-sample
bin/radical-synapse-setup.sh
bin/radical-synapse-stats
bin/radical-synapse-stats.plot
bin/radical-synapse-version
bin/test_openmp.sh
src/radical.synapse.egg-info/PKG-INFO
src/radical.synapse.egg-info/SOURCES.txt
src/radical.synapse.egg-info/dependency_links.txt
src/radical.synapse.egg-info/not-zip-safe
src/radical.synapse.egg-info/requires.txt
src/radical.synapse.egg-info/top_level.txt
src/radical/synapse/VERSION
src/radical/synapse/__init__.py
src/radical/synapse/description.py
src/radical/synapse/synapse.py
src/radical/synapse/synapsify.py
src/radical/synapse/atoms/__init__.py
src/radical/synapse/atoms/atoms.c
src/radical/synapse/atoms/atoms.h
src/radical/synapse/atoms/base.py
src/radical/synapse/atoms/compute.py
src/radical/synapse/atoms/constants.py
src/radical/synapse/atoms/memory.py
src/radical/synapse/atoms/network.py
src/radical/synapse/atoms/storage.py
src/radical/synapse/atoms/synapse_compute.c
src/radical/synapse/atoms/synapse_compute_asm.c
src/radical/synapse/atoms/synapse_compute_test.c
src/radical/synapse/atoms/synapse_memory.c
src/radical/synapse/atoms/synapse_network.c
src/radical/synapse/atoms/synapse_storage.c
src/radical/synapse/atoms/synapse_time.c
src/radical/synapse/atoms/timer.py
src/radical/synapse/atoms/ext_lib/Makefile
src/radical/synapse/atoms/ext_lib/atom_compute_extlib.c
src/radical/synapse/atoms/ext_lib/atom_compute_extlib.h
src/radical/synapse/utils/__init__.py
src/radical/synapse/utils/misc.py
src/radical/synapse/watcher/__init__.py
src/radical/synapse/watcher/watcher_base.py
src/radical/synapse/watcher/watcher_cpu.py
src/radical/synapse/watcher/watcher_mem.py
src/radical/synapse/watcher/watcher_sto.py
